totoms/TotoDelegateDecorator.py
totoms/TotoLogger.py
totoms/TotoMicroservice.py
totoms/TotoTokenVerifier.py
totoms/__init__.py
totoms/py.typed
totoms/__pycache__/TotoDelegateDecorator.cpython-312.pyc
totoms/__pycache__/TotoLogger.cpython-312.pyc
totoms/__pycache__/TotoMicroservice.cpython-312.pyc
totoms/__pycache__/TotoTokenVerifier.cpython-312.pyc
totoms/__pycache__/__init__.cpython-312.pyc
totoms/api/APIControllerOptions.py
totoms/api/APIControllerProps.py
totoms/api/TotoAPIController.py
totoms/api/__init__.py
totoms/api/__pycache__/APIControllerOptions.cpython-312.pyc
totoms/api/__pycache__/APIControllerProps.cpython-312.pyc
totoms/api/__pycache__/TotoAPIController.cpython-312.pyc
totoms/api/__pycache__/__init__.cpython-312.pyc
totoms/evt/Interfaces.py
totoms/evt/MessageBusConfig.py
totoms/evt/MessageDestination.py
totoms/evt/TotoMessage.py
totoms/evt/TotoMessageBus.py
totoms/evt/TotoMessageHandler.py
totoms/evt/__init__.py
totoms/evt/__pycache__/Interfaces.cpython-312.pyc
totoms/evt/__pycache__/MessageBusConfig.cpython-312.pyc
totoms/evt/__pycache__/MessageDestination.cpython-312.pyc
totoms/evt/__pycache__/TotoMessage.cpython-312.pyc
totoms/evt/__pycache__/TotoMessageBus.cpython-312.pyc
totoms/evt/__pycache__/TotoMessageHandler.cpython-312.pyc
totoms/evt/__pycache__/__init__.cpython-312.pyc
totoms/evt/impl/GCPPubSub.py
totoms/evt/impl/SNS.py
totoms/evt/impl/__init__.py
totoms/evt/impl/__pycache__/GCPPubSub.cpython-312.pyc
totoms/evt/impl/__pycache__/SNS.cpython-312.pyc
totoms/evt/impl/__pycache__/__init__.cpython-312.pyc
totoms/model/ExecutionContext.py
totoms/model/Hyperscaler.py
totoms/model/PathOptions.py
totoms/model/TotoAPIEndpoint.py
totoms/model/TotoConfig.py
totoms/model/TotoEnvironment.py
totoms/model/UserContext.py
totoms/model/ValidationResult.py
totoms/model/__init__.py
totoms/model/singleton.py
totoms/model/__pycache__/ExecutionContext.cpython-312.pyc
totoms/model/__pycache__/Hyperscaler.cpython-312.pyc
totoms-1.2.0.dist-info/licenses/LICENSE
totoms-1.2.0.dist-info/METADATA
totoms-1.2.0.dist-info/WHEEL
totoms-1.2.0.dist-info/top_level.txt
totoms-1.2.0.dist-info/RECORD
